[
    {
        "Date": "14/12/2024 22:57:49",
        "Erreur": [
            "station:011 less than 10%",
            "station:020 less than 10%",
            "station:023 less than 10%",
            "station:026 less than 10%",
            "station:027 less than 10%",
            "station:028 less than 10%",
            "station:034 less than 10%",
            "station:035 less than 10%",
            "station:036 less than 10%",
            "station:044 less than 10%",
            "station:047 less than 10%",
            "station:054 less than 10%",
            "station:059 less than 10%"
        ]
    },
    {
        "Date": "14/12/2024 23:23:20",
        "Erreur": [
            "station:011 less than 10%",
            "station:020 less than 10%",
            "station:023 less than 10%",
            "station:026 less than 10%",
            "station:027 less than 10%",
            "station:028 less than 10%",
            "station:035 less than 10%",
            "station:036 less than 10%",
            "station:044 less than 10%",
            "station:047 less than 10%",
            "station:054 less than 10%",
            "station:059 less than 10%"
        ]
    },
    {
        "Date": "14/12/2024 23:40:58",
        "Erreur": [
            "station:008 less than 10%",
            "station:011 less than 10%",
            "station:020 less than 10%",
            "station:023 less than 10%",
            "station:026 less than 10%",
            "station:027 less than 10%",
            "station:028 less than 10%",
            "station:034 less than 10%",
            "station:035 less than 10%",
            "station:036 less than 10%",
            "station:044 less than 10%",
            "station:047 less than 10%",
            "station:054 less than 10%",
            "station:059 less than 10%"
        ]
    },
    {
        "Date": "14/12/2024 23:56:35",
        "Erreur": [
            "station:008 less than 10%",
            "station:011 less than 10%",
            "station:020 less than 10%",
            "station:023 less than 10%",
            "station:026 less than 10%",
            "station:027 less than 10%",
            "station:028 less than 10%",
            "station:034 less than 10%",
            "station:035 less than 10%",
            "station:036 less than 10%",
            "station:044 less than 10%",
            "station:047 less than 10%",
            "station:054 less than 10%",
            "station:059 less than 10%"
        ]
    },
    {
        "Date": "15/12/2024 00:21:07",
        "Erreur": [
            "station:008 less than 10%",
            "station:011 less than 10%",
            "station:020 less than 10%",
            "station:023 less than 10%",
            "station:027 less than 10%",
            "station:028 less than 10%",
            "station:034 less than 10%",
            "station:035 less than 10%",
            "station:036 less than 10%",
            "station:044 less than 10%",
            "station:054 less than 10%",
            "station:059 less than 10%"
        ]
    },
    {
        "Date": "15/12/2024 00:38:19",
        "Erreur": [
            "station:008 less than 10%",
            "station:011 less than 10%",
            "station:020 less than 10%",
            "station:023 less than 10%",
            "station:027 less than 10%",
            "station:028 less than 10%",
            "station:034 less than 10%",
            "station:035 less than 10%",
            "station:036 less than 10%",
            "station:044 less than 10%",
            "station:054 less than 10%",
            "station:059 less than 10%"
        ]
    },
    {
        "Date": "15/12/2024 00:49:34",
        "Erreur": [
            "station:008 less than 10%",
            "station:011 less than 10%",
            "station:020 less than 10%",
            "station:023 less than 10%",
            "station:027 less than 10%",
            "station:028 less than 10%",
            "station:034 less than 10%",
            "station:035 less than 10%",
            "station:036 less than 10%",
            "station:044 less than 10%",
            "station:054 less than 10%",
            "station:059 less than 10%"
        ]
    },
    {
        "Date": "15/12/2024 01:43:46",
        "Erreur": [
            "station:008 less than 10%",
            "station:011 less than 10%",
            "station:020 less than 10%",
            "station:027 less than 10%",
            "station:028 less than 10%",
            "station:034 less than 10%",
            "station:035 less than 10%",
            "station:036 less than 10%",
            "station:044 less than 10%",
            "station:054 less than 10%",
            "station:059 less than 10%",
            "station:060 less than 10%"
        ]
    },
    {
        "Date": "15/12/2024 03:25:34",
        "Erreur": [
            "station:008 less than 10%",
            "station:009 less than 10%",
            "station:011 less than 10%",
            "station:020 less than 10%",
            "station:026 less than 10%",
            "station:027 less than 10%",
            "station:028 less than 10%",
            "station:034 less than 10%",
            "station:035 less than 10%",
            "station:044 less than 10%",
            "station:047 less than 10%",
            "station:054 less than 10%",
            "station:059 less than 10%",
            "station:060 less than 10%"
        ]
    },
    {
        "Date": "15/12/2024 04:25:44",
        "Erreur": [
            "station:002 less than 10%",
            "station:008 less than 10%",
            "station:009 less than 10%",
            "station:011 less than 10%",
            "station:020 less than 10%",
            "station:023 less than 10%",
            "station:026 less than 10%",
            "station:027 less than 10%",
            "station:028 less than 10%",
            "station:034 less than 10%",
            "station:035 less than 10%",
            "station:044 less than 10%",
            "station:047 less than 10%",
            "station:054 less than 10%",
            "station:059 less than 10%",
            "station:060 less than 10%"
        ]
    },
    {
        "Date": "15/12/2024 04:51:42",
        "Erreur": [
            "station:002 less than 10%",
            "station:008 less than 10%",
            "station:009 less than 10%",
            "station:011 less than 10%",
            "station:020 less than 10%",
            "station:023 less than 10%",
            "station:026 less than 10%",
            "station:027 less than 10%",
            "station:028 less than 10%",
            "station:034 less than 10%",
            "station:035 less than 10%",
            "station:044 less than 10%",
            "station:047 less than 10%",
            "station:054 less than 10%",
            "station:059 less than 10%",
            "station:060 less than 10%"
        ]
    },
    {
        "Date": "15/12/2024 05:23:55",
        "Erreur": [
            "station:002 less than 10%",
            "station:009 less than 10%",
            "station:011 less than 10%",
            "station:020 less than 10%",
            "station:023 less than 10%",
            "station:026 less than 10%",
            "station:027 less than 10%",
            "station:028 less than 10%",
            "station:034 less than 10%",
            "station:035 less than 10%",
            "station:047 less than 10%",
            "station:054 less than 10%",
            "station:059 less than 10%",
            "station:060 less than 10%"
        ]
    },
    {
        "Date": "15/12/2024 05:43:10",
        "Erreur": [
            "station:002 less than 10%",
            "station:009 less than 10%",
            "station:011 less than 10%",
            "station:020 less than 10%",
            "station:023 less than 10%",
            "station:026 less than 10%",
            "station:027 less than 10%",
            "station:028 less than 10%",
            "station:034 less than 10%",
            "station:047 less than 10%",
            "station:054 less than 10%",
            "station:059 less than 10%",
            "station:060 less than 10%"
        ]
    },
    {
        "Date": "15/12/2024 05:57:02",
        "Erreur": [
            "station:002 less than 10%",
            "station:009 less than 10%",
            "station:011 less than 10%",
            "station:020 less than 10%",
            "station:023 less than 10%",
            "station:026 less than 10%",
            "station:027 less than 10%",
            "station:028 less than 10%",
            "station:034 less than 10%",
            "station:047 less than 10%",
            "station:054 less than 10%",
            "station:059 less than 10%",
            "station:060 less than 10%"
        ]
    },
    {
        "Date": "15/12/2024 06:22:18",
        "Erreur": [
            "station:002 less than 10%",
            "station:009 less than 10%",
            "station:011 less than 10%",
            "station:020 less than 10%",
            "station:023 less than 10%",
            "station:026 less than 10%",
            "station:027 less than 10%",
            "station:028 less than 10%",
            "station:034 less than 10%",
            "station:047 less than 10%",
            "station:054 less than 10%",
            "station:059 less than 10%",
            "station:060 less than 10%"
        ]
    },
    {
        "Date": "15/12/2024 06:41:06",
        "Erreur": [
            "station:002 less than 10%",
            "station:009 less than 10%",
            "station:011 less than 10%",
            "station:020 less than 10%",
            "station:023 less than 10%",
            "station:026 less than 10%",
            "station:027 less than 10%",
            "station:028 less than 10%",
            "station:034 less than 10%",
            "station:047 less than 10%",
            "station:054 less than 10%",
            "station:059 less than 10%",
            "station:060 less than 10%"
        ]
    },
    {
        "Date": "15/12/2024 06:56:55",
        "Erreur": [
            "station:002 less than 10%",
            "station:009 less than 10%",
            "station:011 less than 10%",
            "station:020 less than 10%",
            "station:023 less than 10%",
            "station:026 less than 10%",
            "station:027 less than 10%",
            "station:028 less than 10%",
            "station:034 less than 10%",
            "station:047 less than 10%",
            "station:054 less than 10%",
            "station:059 less than 10%",
            "station:060 less than 10%"
        ]
    },
    {
        "Date": "15/12/2024 07:32:08",
        "Erreur": [
            "station:002 less than 10%",
            "station:009 less than 10%",
            "station:011 less than 10%",
            "station:020 less than 10%",
            "station:023 less than 10%",
            "station:026 less than 10%",
            "station:027 less than 10%",
            "station:028 less than 10%",
            "station:034 less than 10%",
            "station:047 less than 10%",
            "station:054 less than 10%",
            "station:059 less than 10%",
            "station:060 less than 10%"
        ]
    },
    {
        "Date": "15/12/2024 07:50:39",
        "Erreur": [
            "station:002 less than 10%",
            "station:009 less than 10%",
            "station:011 less than 10%",
            "station:020 less than 10%",
            "station:023 less than 10%",
            "station:026 less than 10%",
            "station:027 less than 10%",
            "station:028 less than 10%",
            "station:034 less than 10%",
            "station:047 less than 10%",
            "station:054 less than 10%",
            "station:059 less than 10%",
            "station:060 less than 10%"
        ]
    },
    {
        "Date": "15/12/2024 08:18:26",
        "Erreur": [
            "station:002 less than 10%",
            "station:009 less than 10%",
            "station:011 less than 10%",
            "station:020 less than 10%",
            "station:023 less than 10%",
            "station:026 less than 10%",
            "station:027 less than 10%",
            "station:028 less than 10%",
            "station:034 less than 10%",
            "station:047 less than 10%",
            "station:054 less than 10%",
            "station:059 less than 10%",
            "station:060 less than 10%"
        ]
    },
    {
        "Date": "15/12/2024 08:30:21",
        "Erreur": [
            "station:002 less than 10%",
            "station:009 less than 10%",
            "station:011 less than 10%",
            "station:020 less than 10%",
            "station:023 less than 10%",
            "station:026 less than 10%",
            "station:027 less than 10%",
            "station:028 less than 10%",
            "station:034 less than 10%",
            "station:047 less than 10%",
            "station:054 less than 10%",
            "station:059 less than 10%",
            "station:060 less than 10%"
        ]
    },
    {
        "Date": "15/12/2024 08:41:36",
        "Erreur": [
            "station:002 less than 10%",
            "station:009 less than 10%",
            "station:011 less than 10%",
            "station:015 less than 10%",
            "station:020 less than 10%",
            "station:023 less than 10%",
            "station:026 less than 10%",
            "station:027 less than 10%",
            "station:028 less than 10%",
            "station:034 less than 10%",
            "station:047 less than 10%",
            "station:054 less than 10%",
            "station:059 less than 10%",
            "station:060 less than 10%"
        ]
    },
    {
        "Date": "15/12/2024 08:57:02",
        "Erreur": [
            "station:002 less than 10%",
            "station:009 less than 10%",
            "station:011 less than 10%",
            "station:015 less than 10%",
            "station:020 less than 10%",
            "station:023 less than 10%",
            "station:026 less than 10%",
            "station:027 less than 10%",
            "station:028 less than 10%",
            "station:034 less than 10%",
            "station:047 less than 10%",
            "station:054 less than 10%",
            "station:059 less than 10%",
            "station:060 less than 10%"
        ]
    },
    {
        "Date": "15/12/2024 09:28:28",
        "Erreur": [
            "Mosson less than 10%",
            "station:002 less than 10%",
            "station:009 less than 10%",
            "station:011 less than 10%",
            "station:015 less than 10%",
            "station:020 less than 10%",
            "station:023 less than 10%",
            "station:026 less than 10%",
            "station:027 less than 10%",
            "station:028 less than 10%",
            "station:034 less than 10%",
            "station:054 less than 10%",
            "station:059 less than 10%",
            "station:060 less than 10%"
        ]
    },
    {
        "Date": "15/12/2024 09:45:15",
        "Erreur": [
            "Mosson less than 10%",
            "station:002 less than 10%",
            "station:009 less than 10%",
            "station:011 less than 10%",
            "station:015 less than 10%",
            "station:020 less than 10%",
            "station:023 less than 10%",
            "station:026 less than 10%",
            "station:027 less than 10%",
            "station:028 less than 10%",
            "station:034 less than 10%",
            "station:054 less than 10%",
            "station:059 less than 10%",
            "station:060 less than 10%"
        ]
    },
    {
        "Date": "15/12/2024 09:56:37",
        "Erreur": [
            "Mosson less than 10%",
            "station:002 less than 10%",
            "station:009 less than 10%",
            "station:011 less than 10%",
            "station:015 less than 10%",
            "station:020 less than 10%",
            "station:023 less than 10%",
            "station:026 less than 10%",
            "station:027 less than 10%",
            "station:028 less than 10%",
            "station:034 less than 10%",
            "station:054 less than 10%",
            "station:059 less than 10%",
            "station:060 less than 10%"
        ]
    },
    {
        "Date": "15/12/2024 10:22:16",
        "Erreur": [
            "Mosson less than 10%",
            "station:002 less than 10%",
            "station:009 less than 10%",
            "station:011 less than 10%",
            "station:015 less than 10%",
            "station:020 less than 10%",
            "station:023 less than 10%",
            "station:026 less than 10%",
            "station:027 less than 10%",
            "station:028 less than 10%",
            "station:034 less than 10%",
            "station:054 less than 10%",
            "station:059 less than 10%",
            "station:060 less than 10%"
        ]
    },
    {
        "Date": "15/12/2024 10:39:19",
        "Erreur": [
            "Mosson less than 10%",
            "station:002 less than 10%",
            "station:009 less than 10%",
            "station:011 less than 10%",
            "station:015 less than 10%",
            "station:020 less than 10%",
            "station:023 less than 10%",
            "station:026 less than 10%",
            "station:027 less than 10%",
            "station:028 less than 10%",
            "station:032 less than 10%",
            "station:034 less than 10%",
            "station:038 less than 10%",
            "station:054 less than 10%",
            "station:059 less than 10%",
            "station:060 less than 10%"
        ]
    },
    {
        "Date": "15/12/2024 10:50:06",
        "Erreur": [
            "Mosson less than 10%",
            "station:002 less than 10%",
            "station:009 less than 10%",
            "station:011 less than 10%",
            "station:015 less than 10%",
            "station:020 less than 10%",
            "station:023 less than 10%",
            "station:026 less than 10%",
            "station:027 less than 10%",
            "station:028 less than 10%",
            "station:032 less than 10%",
            "station:034 less than 10%",
            "station:038 less than 10%",
            "station:054 less than 10%",
            "station:059 less than 10%",
            "station:060 less than 10%"
        ]
    },
    {
        "Date": "15/12/2024 11:08:45",
        "Erreur": [
            "station:002 less than 10%",
            "station:009 less than 10%",
            "station:011 less than 10%",
            "station:015 less than 10%",
            "station:020 less than 10%",
            "station:023 less than 10%",
            "station:026 less than 10%",
            "station:027 less than 10%",
            "station:028 less than 10%",
            "station:032 less than 10%",
            "station:034 less than 10%",
            "station:038 less than 10%",
            "station:054 less than 10%",
            "station:059 less than 10%"
        ]
    },
    {
        "Date": "15/12/2024 11:33:44",
        "Erreur": [
            "station:002 less than 10%",
            "station:008 less than 10%",
            "station:009 less than 10%",
            "station:011 less than 10%",
            "station:015 less than 10%",
            "station:020 less than 10%",
            "station:023 less than 10%",
            "station:026 less than 10%",
            "station:027 less than 10%",
            "station:028 less than 10%",
            "station:032 less than 10%",
            "station:034 less than 10%",
            "station:038 less than 10%",
            "station:054 less than 10%",
            "station:059 less than 10%"
        ]
    },
    {
        "Date": "15/12/2024 11:46:48",
        "Erreur": [
            "station:002 less than 10%",
            "station:008 less than 10%",
            "station:009 less than 10%",
            "station:011 less than 10%",
            "station:015 less than 10%",
            "station:020 less than 10%",
            "station:023 less than 10%",
            "station:026 less than 10%",
            "station:027 less than 10%",
            "station:028 less than 10%",
            "station:032 less than 10%",
            "station:034 less than 10%",
            "station:038 less than 10%",
            "station:054 less than 10%",
            "station:059 less than 10%"
        ]
    },
    {
        "Date": "15/12/2024 11:58:10",
        "Erreur": [
            "station:002 less than 10%",
            "station:008 less than 10%",
            "station:009 less than 10%",
            "station:011 less than 10%",
            "station:015 less than 10%",
            "station:020 less than 10%",
            "station:023 less than 10%",
            "station:026 less than 10%",
            "station:027 less than 10%",
            "station:028 less than 10%",
            "station:032 less than 10%",
            "station:034 less than 10%",
            "station:038 less than 10%",
            "station:054 less than 10%",
            "station:059 less than 10%"
        ]
    },
    {
        "Date": "15/12/2024 12:18:41",
        "Erreur": [
            "station:002 less than 10%",
            "station:008 less than 10%",
            "station:009 less than 10%",
            "station:011 less than 10%",
            "station:015 less than 10%",
            "station:020 less than 10%",
            "station:023 less than 10%",
            "station:026 less than 10%",
            "station:027 less than 10%",
            "station:028 less than 10%",
            "station:032 less than 10%",
            "station:034 less than 10%",
            "station:038 less than 10%",
            "station:054 less than 10%",
            "station:059 less than 10%"
        ]
    },
    {
        "Date": "15/12/2024 12:29:57",
        "Erreur": [
            "station:002 less than 10%",
            "station:008 less than 10%",
            "station:009 less than 10%",
            "station:011 less than 10%",
            "station:015 less than 10%",
            "station:020 less than 10%",
            "station:023 less than 10%",
            "station:026 less than 10%",
            "station:027 less than 10%",
            "station:028 less than 10%",
            "station:032 less than 10%",
            "station:034 less than 10%",
            "station:038 less than 10%",
            "station:054 less than 10%",
            "station:059 less than 10%"
        ]
    },
    {
        "Date": "15/12/2024 12:41:11",
        "Erreur": [
            "station:002 less than 10%",
            "station:008 less than 10%",
            "station:009 less than 10%",
            "station:011 less than 10%",
            "station:015 less than 10%",
            "station:020 less than 10%",
            "station:021 less than 10%",
            "station:023 less than 10%",
            "station:026 less than 10%",
            "station:027 less than 10%",
            "station:028 less than 10%",
            "station:032 less than 10%",
            "station:034 less than 10%",
            "station:038 less than 10%",
            "station:054 less than 10%",
            "station:059 less than 10%"
        ]
    },
    {
        "Date": "15/12/2024 12:56:35",
        "Erreur": [
            "Arc de Triomphe less than 10%",
            "station:002 less than 10%",
            "station:008 less than 10%",
            "station:009 less than 10%",
            "station:011 less than 10%",
            "station:015 less than 10%",
            "station:020 less than 10%",
            "station:021 less than 10%",
            "station:023 less than 10%",
            "station:026 less than 10%",
            "station:027 less than 10%",
            "station:028 less than 10%",
            "station:032 less than 10%",
            "station:034 less than 10%",
            "station:038 less than 10%",
            "station:054 less than 10%"
        ]
    },
    {
        "Date": "15/12/2024 13:42:29",
        "Erreur": [
            "Arc de Triomphe less than 10%",
            "station:002 less than 10%",
            "station:008 less than 10%",
            "station:009 less than 10%",
            "station:011 less than 10%",
            "station:015 less than 10%",
            "station:020 less than 10%",
            "station:023 less than 10%",
            "station:026 less than 10%",
            "station:027 less than 10%",
            "station:028 less than 10%",
            "station:032 less than 10%",
            "station:034 less than 10%",
            "station:038 less than 10%",
            "station:054 less than 10%"
        ]
    },
    {
        "Date": "15/12/2024 14:13:14",
        "Erreur": [
            "Arc de Triomphe less than 10%",
            "station:002 less than 10%",
            "station:008 less than 10%",
            "station:009 less than 10%",
            "station:011 less than 10%",
            "station:015 less than 10%",
            "station:020 less than 10%",
            "station:023 less than 10%",
            "station:026 less than 10%",
            "station:027 less than 10%",
            "station:028 less than 10%",
            "station:032 less than 10%",
            "station:034 less than 10%",
            "station:038 less than 10%",
            "station:054 less than 10%"
        ]
    },
    {
        "Date": "15/12/2024 14:34:44",
        "Erreur": [
            "Arc de Triomphe less than 10%",
            "station:002 less than 10%",
            "station:009 less than 10%",
            "station:011 less than 10%",
            "station:015 less than 10%",
            "station:020 less than 10%",
            "station:023 less than 10%",
            "station:026 less than 10%",
            "station:027 less than 10%",
            "station:028 less than 10%",
            "station:032 less than 10%",
            "station:034 less than 10%",
            "station:038 less than 10%",
            "station:047 less than 10%",
            "station:054 less than 10%"
        ]
    }
]